poetryjpgtopng/__init__.py
poetryjpgtopng/jpgTopng.py
poetryjpgtopng-0.1.2.dist-info/METADATA
poetryjpgtopng-0.1.2.dist-info/WHEEL
poetryjpgtopng-0.1.2.dist-info/RECORD
