Metadata-Version: 2.1
Name: poetryjpgtopng
Version: 0.1.2
Summary: 
Author: 极客小方
Author-email: 141008618+GeekFong@users.noreply.github.com
Requires-Python: >=3.9,<4.0
Classifier: Programming Language :: Python :: 3
Classifier: Programming Language :: Python :: 3.9
Classifier: Programming Language :: Python :: 3.10
Classifier: Programming Language :: Python :: 3.11
Classifier: Programming Language :: Python :: 3.12
Requires-Dist: pillow (>=10.1.0,<11.0.0)
